notebookmanipulation_pkg/__init__.py
notebookmanipulation_pkg/googleslides.py
notebookmanipulation_pkg/imageverify.py
notebookmanipulation_pkg/metadataframes.py
notebookmanipulation_pkg/notebookchecks.py
notebookmanipulation_pkg/notebookformatter.py
notebookmanipulation_pkg/textcheck.py
notebookmanipulation_pkg_ALPHA-0.0.3.dist-info/LICENSE
notebookmanipulation_pkg_ALPHA-0.0.3.dist-info/METADATA
notebookmanipulation_pkg_ALPHA-0.0.3.dist-info/WHEEL
notebookmanipulation_pkg_ALPHA-0.0.3.dist-info/top_level.txt
notebookmanipulation_pkg_ALPHA-0.0.3.dist-info/RECORD
