Metadata-Version: 2.1
Name: notebookmanipulation-pkg-ALPHA
Version: 0.0.3
Summary: A simple package made by Callysto containing various functions to maintain and update Jupyter Notebooks. Written with educators in mind.
Home-page: https://github.com/lisancao/notebook-manipulation/tree/package_development
Author: Lisa Cao, David Hays, with Contributions from Cybera
Author-email: lisa.cao@cybera.ca
License: UNKNOWN
Platform: UNKNOWN
Classifier: Development Status :: 2 - Pre-Alpha
Classifier: Framework :: Jupyter
Classifier: Programming Language :: Python :: 3
Classifier: Operating System :: OS Independent
Requires-Python: >=3.7
